lenco/__init__.py
lenco/client.py
lenco/exceptions.py
lenco/http.py
lenco/resources.py
lenco/types.py
lenco/webhooks.py
lenco_python-2.0.0.dist-info/METADATA
lenco_python-2.0.0.dist-info/WHEEL
lenco_python-2.0.0.dist-info/licenses/LICENSE
lenco_python-2.0.0.dist-info/RECORD
