Metadata-Version: 2.4
Name: lenco-python
Version: 2.0.0
Summary: Python SDK for Lenco API - Payments, Transfers, Collections
Project-URL: Documentation, https://docs.lenco.co
Project-URL: Repository, https://github.com/alexasomba/lenco-python
Project-URL: Issues, https://github.com/alexasomba/lenco-python/issues
Author-email: Alexander Asomba <alex@asomba.com>
License-Expression: MIT
License-File: LICENSE
Keywords: africa,api,fintech,lenco,mobile-money,payments,sdk
Classifier: Development Status :: 5 - Production/Stable
Classifier: Intended Audience :: Developers
Classifier: License :: OSI Approved :: MIT License
Classifier: Operating System :: OS Independent
Classifier: Programming Language :: Python :: 3
Classifier: Programming Language :: Python :: 3.9
Classifier: Programming Language :: Python :: 3.10
Classifier: Programming Language :: Python :: 3.11
Classifier: Programming Language :: Python :: 3.12
Classifier: Topic :: Software Development :: Libraries :: Python Modules
Classifier: Typing :: Typed
Requires-Python: >=3.9
Requires-Dist: httpx>=0.25.0
Requires-Dist: pydantic>=2.0.0
Provides-Extra: dev
Requires-Dist: mypy>=1.0.0; extra == 'dev'
Requires-Dist: pytest-asyncio>=0.21.0; extra == 'dev'
Requires-Dist: pytest-cov>=4.0.0; extra == 'dev'
Requires-Dist: pytest>=7.0.0; extra == 'dev'
Requires-Dist: ruff>=0.1.0; extra == 'dev'
